<?xml version="1.0" encoding="utf-8" ?><dwsync><file name="jquery-1.7.1.min.js" server="ftp.domeneshop.no/www/preprod/" local="3410296925" remote="12005503652" /><file name="jquery.isotope.min.js" server="ftp.domeneshop.no/www/preprod/" local="3412075837" remote="12005503652" /><file name="jquery.mousewheel.js" server="ftp.domeneshop.no/www/preprod/" local="3412797530" remote="12005503652" /><file name="script.js" server="ftp.domeneshop.no/www/preprod/" local="3415709005" remote="16300603668" /><file name=".DS_Store" server="ftp.domeneshop.no/www/preprod/" local="3415576177" remote="12005503652" /><file name="jquery.jscrollpane.min.js" server="ftp.domeneshop.no/www/preprod/" local="3412797530" remote="12005503652" /><file name="mwheelIntent.js" server="ftp.domeneshop.no/www/preprod/" local="3412797530" remote="12005503652" /><file name="slides.min.jquery.js" server="ftp.domeneshop.no/www/preprod/" local="3398103383" remote="16300594548" /></dwsync>